txtcleanen/__init__.py
txtcleanen/txtcleanen.py
txtcleanen-1.0.0.dist-info/License
txtcleanen-1.0.0.dist-info/METADATA
txtcleanen-1.0.0.dist-info/WHEEL
txtcleanen-1.0.0.dist-info/top_level.txt
txtcleanen-1.0.0.dist-info/RECORD
