Metadata-Version: 2.1
Name: txtcleanen
Version: 1.0.0
Summary: A lightweight Python package to clean English text by removing HTML tags, URLs, emojis, digits, and punctuation.
Author: Md. Ismiel Hossen Abir
Author-email: ismielabir1971@gmail.com
Classifier: Programming Language :: Python :: 3
Classifier: Intended Audience :: Developers
Classifier: License :: OSI Approved :: MIT License
Classifier: Topic :: Text Processing :: Filters
Classifier: Topic :: Software Development :: Libraries :: Python Modules
Classifier: Operating System :: OS Independent
Requires-Python: >=3.6
License-File: License
